eventum_asgi/__init__.py
eventum_asgi/app.py
eventum_asgi/connection.py
eventum_asgi/event_loop.py
eventum_asgi/event_router.py
eventum_asgi/events/__init__.py
eventum_asgi/events/base_event.py
eventum_asgi/events/validation_error.py
eventum_asgi/exceptions/__init__.py
eventum_asgi/exceptions/disconnect.py
eventum_asgi/exceptions/http_exception.py
eventum_asgi/exceptions/required_headers_missing.py
eventum_asgi/exceptions/route_not_found.py
eventum_asgi/exceptions/validation.py
eventum_asgi/handshake_router.py
eventum_asgi/http_eventum/__init__.py
eventum_asgi/http_eventum/_http_bad_request.py
eventum_asgi/http_eventum/response.py
eventum_asgi/lifespan.py
eventum_asgi/middleware/__init__.py
eventum_asgi/middleware/exceptions_middleware.py
eventum_asgi/middleware/server_error_middleware.py
eventum_asgi/middleware_chain.py
eventum_asgi/models/__init__.py
eventum_asgi/models/headers.py
eventum_asgi/testclient.py
eventum_asgi/types.py
eventum_asgi-0.0.2.dist-info/LICENSE.txt
eventum_asgi-0.0.2.dist-info/METADATA
eventum_asgi-0.0.2.dist-info/WHEEL
eventum_asgi-0.0.2.dist-info/RECORD
